{
  "visibleCount": 4,
  "lives": [
    {
      "type": "youtube",
      "#id": "https://www.youtube.com/embed/Iwxt5qH2Vto?autoplay=1&loop=1&list=PLzxE-FyHBDAdbtATJXjEuHXxQd8EaD8BG",
      "#title": "OFFLINE",
      "active": false
    },
    {
      "type": "facebook",
      "#id": "https://www.facebook.com/icablenews/videos/1449455668529568/",
      "#title": "有線新聞 i-Cable News",
      "#source": "有線新聞 i-Cable News",
      "active": false
    },
    {
      "type": "facebook",
      "#id": "https://www.facebook.com/RTHKVNEWS/videos/908687276159596/",
      "#title": "香港電台視像新聞 RTHK VNEWS",
      "#source": "香港電台 RTHK",
      "active": true
    },
    {
      "type": "facebook",
      "#id": "https://www.facebook.com/RTHKVNEWS/videos/429307981005876/",
      "#title": "香港電台視像新聞 RTHK VNEWS (2)",
      "#source": "香港電台 RTHK",
      "active": false
    },
    {
      "type": "facebook",
      "#id": "https://www.facebook.com/rthk31thisweek/videos/687350618360061/",
      "#title": "香港電台視點31",
      "#source": "香港電台 RTHK",
      "active": false
    },
    {
      "type": "facebook",
      "#id": "https://www.facebook.com/rthkPCA/videos/647175459121611/",
      "#title": "港台電視部－公共事務組",
      "#source": "香港電台 RTHK",
      "active": false
    },
    {
      "type": "facebook",
      "#id": "https://www.facebook.com/hk.nextmedia/videos/652140275307957/",
      "#title": "蘋果 fb live",
      "#source": "香港蘋果日報 Apple Daily HK",
      "active": false
    },
    {
      "type": "facebook",
      "#id": "https://www.facebook.com/hk.nextmedia/videos/407788506527470/",
      "#title": "蘋果 fb live (2)",
      "#source": "香港蘋果日報 Apple Daily HK",
      "active": false
    },
    {
      "type": "youtube",
      "#id": "https://www.youtube.com/embed/NRlng2MaOT0",
      "#title": "蘋果 Youtube live",
      "#source": "香港蘋果日報 Apple Daily HK",
      "active": true
    },
    {
      "type": "facebook",
      "#id": "https://www.facebook.com/now.comNews/videos/2384234428296744/",
      "#title": "Now 新聞 (Facebook)",
      "#source": "Now 新聞 Now News",
      "active": false
    },
    {
      "type": "youtube",
      "#id": "https://www.youtube.com/embed/Vne9Aya-ZP8",
      "#title": "Now 新聞 (Youtube)",
      "#source": "Now 新聞 Now News",
      "active": true
    },
    {
      "type": "facebook",
      "#id": "https://www.facebook.com/standnewshk/videos/478839599601793/",
      "#title": "立場直播",
      "#source": "立場新聞 Stand News",
      "active": true
    },
    {
      "type": "facebook",
      "#id": "https://www.facebook.com/standnewshk/videos/406623556634907/",
      "#title": "立場直播 - 維園反暴力集會",
      "#source": "立場新聞 Stand News",
      "active": true
    },
    {
      "type": "facebook",
      "#id": "https://www.facebook.com/standnewshk/videos/513270949410326/",
      "#title": "立場直播 (3)",
      "#source": "立場新聞 Stand News",
      "active": false
    },
    {
      "type": "facebook",
      "#id": "https://www.facebook.com/standnewshk/videos/1102667026589341/",
      "#title": "立場直播 (4)",
      "#source": "立場新聞 Stand News",
      "active": false
    },
    {
      "type": "facebook",
      "#id": "https://www.facebook.com/standnewshk/videos/808370609596773/",
      "#title": "立場直播 (5)",
      "#source": "立場新聞 Stand News",
      "active": false
    },
    {
      "type": "facebook",
      "#id": "https://www.facebook.com/standnewshk/videos/2441740199251282/",
      "#title": "立場直播 (6)",
      "#source": "立場新聞 Stand News",
      "active": false
    },
    {
      "type": "facebook",
      "#id": "https://www.facebook.com/inmediahk/videos/368132070552514/",
      "#title": "獨媒直播",
      "#source": "香港獨立媒體網 inmediahk.net",
      "active": true
    },
    {
      "type": "facebook",
      "#id": "https://www.facebook.com/inmediahk/videos/903290560026520/",
      "#title": "獨媒直播 (2)",
      "#source": "香港獨立媒體網 inmediahk.net",
      "active": false
    },
    {
      "type": "facebook",
      "#id": "https://www.facebook.com/hongkongfp/videos/393596677932543/",
      "#title": "Hong Kong Free Press HKFP",
      "#source": "Hong Kong Free Press HKFP",
      "active": false
    },
    {
      "type": "facebook",
      "#id": "https://www.facebook.com/hongkongfp/videos/2459130657483865/",
      "#title": "Hong Kong Free Press HKFP (2)",
      "#source": "Hong Kong Free Press HKFP",
      "active": false
    },
    {
      "type": "facebook",
      "#id": "https://www.facebook.com/hongkongfp/videos/2089818064463323/",
      "#title": "Hong Kong Free Press HKFP (3)",
      "#source": "Hong Kong Free Press HKFP",
      "active": false
    },
    {
      "type": "facebook",
      "#id": "https://www.facebook.com/theinitium/videos/1075846972609633/",
      "#title": "端傳媒 Initium Media",
      "#source": "端傳媒 Initium Media",
      "active": false
    },
    {
      "type": "facebook",
      "#id": "https://www.facebook.com/UPMEDIA.MG/videos/419872271938391/",
      "#title": "上報 Up Media",
      "#source": "上報 Up Media",
      "active": false
    },
    {
      "type": "facebook",
      "#id": "https://www.facebook.com/hk01.news/videos/395562504426001/",
      "#title": "01直播",
      "#source": "香港01 HK01",
      "active": true
    },
    {
      "type": "facebook",
      "#id": "https://www.facebook.com/hk01.news/videos/375088403191926/",
      "#title": "01直播 - 維園反暴力集會",
      "#source": "香港01 HK01",
      "active": true
    },
    {
      "type": "facebook",
      "#id": "https://www.facebook.com/onccnews/videos/895643380793305/",
      "#title": "東網直播",
      "#source": "東網／東方日報 on.cc",
      "active": true
    },
    {
      "type": "facebook",
      "#id": "https://www.facebook.com/onccnews/videos/581417002387461/",
      "#title": "東網直播 - 維園反暴力集會",
      "#source": "東網／東方日報 on.cc",
      "active": true
    },
    {
      "type": "facebook",
      "#id": "https://www.facebook.com/mingpaoinews/videos/2275354805895203/",
      "#title": "明報即時新聞 Mingpao News",
      "#source": "明報即時新聞 Mingpao News",
      "active": false
    },
    { 
      "type": "youtube",
      "#id": "https://www.youtube.com/embed/OqwAXNgs3eE",
      "#title": "China Uncensored",
      "#source": "China Uncensored",
      "active": false
    },
    {
      "type": "facebook",
      "#id": "https://www.facebook.com/YahooHongKongNews/videos/218700195697905/",
      "#title": "雅虎香港新聞 Yahoo HK News",
      "#source": "雅虎香港新聞 Yahoo HK News",
      "active": true
    },
    {
      "type": "facebook",
      "#id": "https://www.facebook.com/atvhongkong/videos/2082019858570364/",
      "#title": "香港追擊搜",
      "#source": "亞視數碼媒體 ATV",
      "active": false
    },
    {
      "type": "facebook",
      "#id": "https://www.facebook.com/ABCNews/videos/414639495801280/",
      "#title": "ABC News",
      "#source": "ABC News",
      "active": false
    },
    {
      "type": "facebook",
      "#id": "https://www.facebook.com/scmp/videos/2341797905911482/",
      "#title": "South China Morning Post",
      "#source": "South China Morning Post",
      "active": false
    },
    {
      "type": "facebook",
      "#id": "https://www.facebook.com/socrec/videos/517946642278425/",
      "#title": "SocREC 直播",
      "#source": "社會記錄頻道 SocREC",
      "active": false
    },
    {
      "type": "facebook",
      "#id": "https://www.facebook.com/socrec/videos/1272677222912146/",
      "#title": "SocREC 直播 (2)",
      "#source": "社會記錄頻道 SocREC",
      "active": false
    },
    {
      "type": "facebook",
      "#id": "https://www.facebook.com/am730hk/videos/368628593836280/",
      "#title": "am730",
      "#source": "am730",
      "active": false
    },
    {
      "type": "facebook",
      "#id": "https://www.facebook.com/passiontimes/videos/768286636919257/",
      "#title": "熱血時報 PassionTimes",
      "#source": "熱血時報 PassionTimes",
      "active": true
    },
    {
      "type": "facebook",
      "#id": "https://www.facebook.com/passiontimes/videos/2367735183273150/",
      "#title": "熱血時報 PassionTimes (2)",
      "#source": "熱血時報 PassionTimes",
      "active": false
    },
    {
      "type": "facebook",
      "#id": "https://www.facebook.com/RTHKVNEWS/videos/695246160897028/",
      "#title": "港台直播 - 維園反暴力集會",
      "#source": "香港電台 RTHK",
      "active": true
    },
    {
      "type": "facebook",
      "#id": "https://www.facebook.com/TMHK.ORG/videos/333404897539976/",
      "#title": "TMHK LIVE",
      "#source": "Truth Media Hong Kong",
      "active": true
    },
    {
      "type": "facebook",
      "#id": "https://www.facebook.com/TMHK.ORG/videos/346929102896223/",
      "#title": "TMHK LIVE (2)",
      "#source": "Truth Media Hong Kong",
      "active": false
    },
    {
      "type": "facebook",
      "#id": "https://www.facebook.com/cuspcusp/videos/379670842686867/",
      "#title": "中大學生報 Chinese University Student Press",
      "#source": "中大學生報 Chinese University Student Press",
      "active": false
    },
    {
      "type": "facebook",
      "#id": "https://www.facebook.com/hkucampustv/videos/2356860621065825/",
      "#title": "香港大學學生會校園電視 Campus TV, HKUSU",
      "#source": "香港大學學生會校園電視 Campus TV, HKUSU",
      "active": false
    },
    {
      "type": "facebook",
      "#id": "https://www.facebook.com/cuhkcampusradio/videos/418139145454213/",
      "#title": "中大校園電台 CUHK Campus Radio",
      "#source": "中大校園電台 CUHK Campus Radio",
      "active": false
    },
    {
      "type": "facebook",
      "#id": "https://www.facebook.com/undergradnews/videos/1295932430559952/",
      "#title": "香港大學學生會學苑即時新聞 Undergrad, H.K.U.S.U. Instant News",
      "#source": "香港大學學生會學苑即時新聞 Undergrad, H.K.U.S.U. Instant News",
      "active": false
    },
    {
      "type": "facebook",
      "#id": "https://www.facebook.com/hsusueb/videos/2455931837799711/",
      "#title": "香港恒生大學學生會編輯委員會 Editorial Board, HSUSU",
      "#source": "香港恒生大學學生會編輯委員會 Editorial Board, HSUSU",
      "active": false
    },
    {
      "type": "facebook",
      "#id": "https://www.facebook.com/EdUHKSUEB/videos/410104506294855/",
      "#title": "香港教育大學學生會編輯委員會 EdUHKSU Editorial Board",
      "#source": "香港教育大學學生會編輯委員會 EdUHKSU Editorial Board ",
      "active": false
    },
    {
      "type": "facebook",
      "#id": "https://www.facebook.com/376552872550155/videos/396882777606543/",
      "#title": "米報 Rice Post",
      "#source": "米報 Rice Post",
      "active": true
    },
    {
      "type": "facebook",
      "#id": "https://www.facebook.com/cityusu.cbc/videos/957733304557661/",
      "#title": "CityUSU",
      "#source": "CityUSU",
      "active": false
    },
    {
      "type": "youtube",
      "#id": "https://www.youtube.com/embed/auLKPYs0M0Q",
      "#title": "Washington Post",
      "#source": "Washington Post",
      "active": false
    },
    {
      "type": "youtube",
      "#id": "https://www.youtube.com/embed/LKtU2oINZeE",
      "#title": "NBC News",
      "#source": "NBC News",
      "active": false
    },
    {
      "type": "youtube",
      "#id": "https://www.youtube.com/embed/VdAuOf82WgA",
      "#title": "Global News",
      "#source": "Global News",
      "active": false
    },
    {
      "type": "youtube",
      "#id": "https://www.youtube.com/embed/VmNIJWcfKyk",
      "#title": "Guardian News",
      "#source": "Guardian News",
      "active": false
    },
    {
      "type": "youtube",
      "#id": "https://www.youtube.com/embed/qfn1Mt3fErU",
      "#title": "Euronews",
      "#source": "Euronews",
      "active": false
    },
    {
      "type": "youtube",
      "#id": "https://www.youtube.com/embed/6JEY13EQU24",
      "#title": "RT",
      "#source": "RT",
      "active": false
    },
    {
      "type": "youtube",
      "#id": "https://www.youtube.com/embed/o-8u_jcLIUc",
      "#title": "RT (2)",
      "#source": "RT",
      "active": false
    },
    {
      "type": "youtube",
      "#id": "https://www.youtube.com/embed/M0-H90HIFP0",
      "#title": "Ruptly",
      "#source": "Ruptly",
      "active": true
    },
    {
      "type": "youtube",
      "#id": "https://www.youtube.com/embed/J-HO__UnlVo",
      "#title": "大紀元時報 The Epoch Times",
      "#source": "大紀元時報 The Epoch Times",
      "active": false
    },
    {
      "type": "youtube",
      "#id": "https://www.youtube.com/embed/UsgJWZypxdY",
      "#title": "852郵報 Post852",
      "#source": "852郵報 Post852",
      "active": false
    },
    {
      "type": "facebook",
      "#id": "https://www.facebook.com/cantonese.rfa/videos/682086355600422/",
      "#title": "自由亞洲粵語 RFA Cantonese",
      "#source": "自由亞洲粵語 RFA Cantonese",
      "active": false
    },
    {
      "type": "facebook",
      "#id": "https://www.facebook.com/setnews/videos/652111198590869/",
      "#title": "三立新聞 SETN",
      "#source": "三立新聞 SETN",
      "active": false
    },
    {
      "type": "facebook",
      "#id": "https://www.facebook.com/HKNewsAgency/videos/1225062807671638/",
      "#title": "香港新聞社 HK News Agency",
      "#source": "香港新聞社 HK News Agency",
      "active": false
    },
    {
      "type": "facebook",
      "#id": "https://www.facebook.com/bbcnewstrad/videos/1584242981706204/",
      "#title": "BBC",
      "#source": "BBC",
      "active": false
    },
    {
      "type": "facebook",
      "#id": "https://www.facebook.com/CivilHumanRightsFront/videos/561905774342746/",
      "#title": "民間人權陣線 Civil Human Rights Front",
      "#source": "民間人權陣線 Civil Human Rights Front",
      "active": false
    },
    {
      "type": "facebook",
      "#id": "https://www.facebook.com/MichaelYonFanPage/videos/523542775052430/",
      "#title": "Michael Yon",
      "#source": "Michael Yon",
      "active": false
    },
    {
      "type": "facebook",
      "#id": "https://www.facebook.com/RTHKcityforum/videos/2056599964649453/",
      "#title": "香港電台城市論壇 RTHK City Forum",
      "#source": "香港電台 RTHK",
      "active": false
    },
    {
      "type": "facebook",
      "#id": "https://www.facebook.com/maddog.hk/videos/303561097111822/",
      "#title": "癲狗日報 Maddog.HK",
      "#source": "癲狗日報 Maddog.HK",
      "active": false
    },
    {
      "type": "facebook",
      "#id": "https://www.facebook.com/news.hkcd/videos/2309266876054169/",
      "#title": "香港商報",
      "#source": "香港商報",
      "active": false
    },
    {
      "type": "facebook",
      "#id": "https://www.facebook.com/tvbsfb/videos/491628851603234/",
      "#title": "TVBS",
      "#source": "TVBS",
      "active": false
    },
    {
      "type": "facebook",
      "#id": "https://www.facebook.com/joshuawongchifung/videos/695329897557186/",
      "#title": "黃之鋒 Joshua Wong",
      "#source": "黃之鋒 Joshua Wong",
      "active": false
    },
    {
      "type": "facebook",
      "#id": "https://www.facebook.com/heiheixd2/videos/2357479397707174/",
      "#title": "Ronnie Hei",
      "#source": "Ronnie Hei",
      "active": false
    }
  ]
}
